{
  "parent": "minecraft:recipes/root",
  "rewards": {
    "recipes": [
      "swem:star_worm_goop"
    ]
  },
  "criteria": {
    "has_star_worm": {
      "trigger": "minecraft:inventory_changed",
      "conditions": {
        "items": [
          {
            "tag": "swem:star_worm"
          }
        ]
      }
    },
    "has_the_recipe": {
      "trigger": "minecraft:recipe_unlocked",
      "conditions": {
        "recipe": "swem:star_worm_goop"
      }
    }
  },
  "requirements": [
    [
      "has_star_worm",
      "has_the_recipe"
    ]
  ]
}